[
    {
        "OrderID": 1125847485,
        "CustomerID": "Cust1",
        "EmployeeID": 1185833385,
        "OrderDate": "/Date(393489179000)/",
        "RequiredDate": "/Date(772455009000)/",
        "ShippedDate": "/Date(508893621000)/",
        "ShipVia": 1332215230,
        "Freight": 42757727205.7533,
        "ShipName": "ShipName1",
        "ShipAddress": "ShipAddress1",
        "ShipCity": "ShipCity1",
        "ShipRegion": "ShipRegion1",
        "ShipPostalCode": "ShipPosta1",
        "ShipCountry": "ShipCountry1",
        "CompanyName": "WHsoCsyZVPAIjubyLRUyMxnLRJmKQqsA",
        "Address": "Address1",
        "City": "City1",
        "Region": "Region1",
        "PostalCode": "PostalCod1",
        "Country": "Country1"
    },
    {
        "OrderID": 2007765222,
        "CustomerID": "Cust2",
        "EmployeeID": 1988520121,
        "OrderDate": "/Date(201284427000)/",
        "RequiredDate": "/Date(1069654383000)/",
        "ShippedDate": "/Date(99942024000)/",
        "ShipVia": 736857440,
        "Freight": 77892379136.756,
        "ShipName": "ShipName2",
        "ShipAddress": "ShipAddress2",
        "ShipCity": "ShipCity2",
        "ShipRegion": "ShipRegion2",
        "ShipPostalCode": "ShipPosta2",
        "ShipCountry": "ShipCountry2",
        "CompanyName": "qTfJngSHVPodstmgOWWDOxpHiuomUSsm",
        "Address": "Address2",
        "City": "City2",
        "Region": "Region2",
        "PostalCode": "PostalCod2",
        "Country": "Country2"
    },
    {
        "OrderID": 1288130380,
        "CustomerID": "Cust3",
        "EmployeeID": 345477013,
        "OrderDate": "/Date(941635909000)/",
        "RequiredDate": "/Date(1086696095000)/",
        "ShippedDate": "/Date(931846385000)/",
        "ShipVia": 157630595,
        "Freight": 47318102489.2255,
        "ShipName": "ShipName3",
        "ShipAddress": "ShipAddress3",
        "ShipCity": "ShipCity3",
        "ShipRegion": "ShipRegion3",
        "ShipPostalCode": "ShipPosta3",
        "ShipCountry": "ShipCountry3",
        "CompanyName": "ehelxlRqdBPXEXLwdEGtQddpjCKcrLUj",
        "Address": "Address3",
        "City": "City3",
        "Region": "Region3",
        "PostalCode": "PostalCod3",
        "Country": "Country3"
    },
    {
        "OrderID": 1453583012,
        "CustomerID": "Cust4",
        "EmployeeID": 901627643,
        "OrderDate": "/Date(1450576032000)/",
        "RequiredDate": "/Date(963413287000)/",
        "ShippedDate": "/Date(464302022000)/",
        "ShipVia": 640327086,
        "Freight": 6541865.8778,
        "ShipName": "ShipName4",
        "ShipAddress": "ShipAddress4",
        "ShipCity": "ShipCity4",
        "ShipRegion": "ShipRegion4",
        "ShipPostalCode": "ShipPosta4",
        "ShipCountry": "ShipCountry4",
        "CompanyName": "jllDWJIlKZpDROeUqgbvlrJrEXlxlaKG",
        "Address": "Address4",
        "City": "City4",
        "Region": "Region4",
        "PostalCode": "PostalCod4",
        "Country": "Country4"
    },
    {
        "OrderID": 2025009179,
        "CustomerID": "Cust5",
        "EmployeeID": 1288337946,
        "OrderDate": "/Date(634932595000)/",
        "RequiredDate": "/Date(1070508046000)/",
        "ShippedDate": "/Date(1312509347000)/",
        "ShipVia": 1130248456,
        "Freight": 3278633486.4795,
        "ShipName": "ShipName5",
        "ShipAddress": "ShipAddress5",
        "ShipCity": "ShipCity5",
        "ShipRegion": "ShipRegion5",
        "ShipPostalCode": "ShipPosta5",
        "ShipCountry": "ShipCountry5",
        "CompanyName": "iHOGBtwTYJrRkXKSxTOPhuPreXAenkAJ",
        "Address": "Address5",
        "City": "City5",
        "Region": "Region5",
        "PostalCode": "PostalCod5",
        "Country": "Country5"
    },
    {
        "OrderID": 41801815,
        "CustomerID": "Cust6",
        "EmployeeID": 1722613550,
        "OrderDate": "/Date(203553011000)/",
        "RequiredDate": "/Date(485846907000)/",
        "ShippedDate": "/Date(142202904000)/",
        "ShipVia": 967850736,
        "Freight": 85375786246.7318,
        "ShipName": "ShipName6",
        "ShipAddress": "ShipAddress6",
        "ShipCity": "ShipCity6",
        "ShipRegion": "ShipRegion6",
        "ShipPostalCode": "ShipPosta6",
        "ShipCountry": "ShipCountry6",
        "CompanyName": "djIXKDmlMiBMpkMxRSovgIShtEJRGPbY",
        "Address": "Address6",
        "City": "City6",
        "Region": "Region6",
        "PostalCode": "PostalCod6",
        "Country": "Country6"
    },
    {
        "OrderID": 1019717327,
        "CustomerID": "Cust7",
        "EmployeeID": 329989799,
        "OrderDate": "/Date(1285837029000)/",
        "RequiredDate": "/Date(1121855334000)/",
        "ShippedDate": "/Date(415803417000)/",
        "ShipVia": 1406778622,
        "Freight": 88223328511.2306,
        "ShipName": "ShipName7",
        "ShipAddress": "ShipAddress7",
        "ShipCity": "ShipCity7",
        "ShipRegion": "ShipRegion7",
        "ShipPostalCode": "ShipPosta7",
        "ShipCountry": "ShipCountry7",
        "CompanyName": "ohbIZfmcCixiFgTRDtGCdOBXFHRQIEAf",
        "Address": "Address7",
        "City": "City7",
        "Region": "Region7",
        "PostalCode": "PostalCod7",
        "Country": "Country7"
    },
    {
        "OrderID": 755805181,
        "CustomerID": "Cust8",
        "EmployeeID": 442965280,
        "OrderDate": "/Date(779344681000)/",
        "RequiredDate": "/Date(519053155000)/",
        "ShippedDate": "/Date(1356642353000)/",
        "ShipVia": 1370920710,
        "Freight": 44041639752.686,
        "ShipName": "ShipName8",
        "ShipAddress": "ShipAddress8",
        "ShipCity": "ShipCity8",
        "ShipRegion": "ShipRegion8",
        "ShipPostalCode": "ShipPosta8",
        "ShipCountry": "ShipCountry8",
        "CompanyName": "eqnDwlVykmEJbOXEBvOwZnKMHDfVeUWm",
        "Address": "Address8",
        "City": "City8",
        "Region": "Region8",
        "PostalCode": "PostalCod8",
        "Country": "Country8"
    },
    {
        "OrderID": 1536556409,
        "CustomerID": "Cust9",
        "EmployeeID": 2044613147,
        "OrderDate": "/Date(297780715000)/",
        "RequiredDate": "/Date(1185042994000)/",
        "ShippedDate": "/Date(1043066123000)/",
        "ShipVia": 1449214989,
        "Freight": 21457070577.8896,
        "ShipName": "ShipName9",
        "ShipAddress": "ShipAddress9",
        "ShipCity": "ShipCity9",
        "ShipRegion": "ShipRegion9",
        "ShipPostalCode": "ShipPosta9",
        "ShipCountry": "ShipCountry9",
        "CompanyName": "DbftxftXuaSbbQXmNwliqaNwJzpXwWOv",
        "Address": "Address9",
        "City": "City9",
        "Region": "Region9",
        "PostalCode": "PostalCod9",
        "Country": "Country9"
    },
    {
        "OrderID": 2128337551,
        "CustomerID": "Cus10",
        "EmployeeID": 213168078,
        "OrderDate": "/Date(1458084640000)/",
        "RequiredDate": "/Date(159376659000)/",
        "ShippedDate": "/Date(744140688000)/",
        "ShipVia": 572241728,
        "Freight": 59782270877.622,
        "ShipName": "ShipName10",
        "ShipAddress": "ShipAddress10",
        "ShipCity": "ShipCity10",
        "ShipRegion": "ShipRegion10",
        "ShipPostalCode": "ShipPost10",
        "ShipCountry": "ShipCountry10",
        "CompanyName": "UfuRqnxZJITbGYLOzosXlrwrRgDTfXxc",
        "Address": "Address10",
        "City": "City10",
        "Region": "Region10",
        "PostalCode": "PostalCo10",
        "Country": "Country10"
    },
    {
        "OrderID": 953563444,
        "CustomerID": "Cus11",
        "EmployeeID": 721093788,
        "OrderDate": "/Date(1454214448000)/",
        "RequiredDate": "/Date(730309325000)/",
        "ShippedDate": "/Date(745253604000)/",
        "ShipVia": 594991878,
        "Freight": 97120335721.4108,
        "ShipName": "ShipName11",
        "ShipAddress": "ShipAddress11",
        "ShipCity": "ShipCity11",
        "ShipRegion": "ShipRegion11",
        "ShipPostalCode": "ShipPost11",
        "ShipCountry": "ShipCountry11",
        "CompanyName": "aPkYUagsAHgcxgpMxQHWdXHCdBSPQKae",
        "Address": "Address11",
        "City": "City11",
        "Region": "Region11",
        "PostalCode": "PostalCo11",
        "Country": "Country11"
    },
    {
        "OrderID": 847950984,
        "CustomerID": "Cus12",
        "EmployeeID": 215765348,
        "OrderDate": "/Date(898672078000)/",
        "RequiredDate": "/Date(557055805000)/",
        "ShippedDate": "/Date(102061196000)/",
        "ShipVia": 628771697,
        "Freight": 32086982182.227,
        "ShipName": "ShipName12",
        "ShipAddress": "ShipAddress12",
        "ShipCity": "ShipCity12",
        "ShipRegion": "ShipRegion12",
        "ShipPostalCode": "ShipPost12",
        "ShipCountry": "ShipCountry12",
        "CompanyName": "UywudbnKTQPrmLAUurYTmBhwWjhebXrS",
        "Address": "Address12",
        "City": "City12",
        "Region": "Region12",
        "PostalCode": "PostalCo12",
        "Country": "Country12"
    },
    {
        "OrderID": 283935563,
        "CustomerID": "Cus13",
        "EmployeeID": 417050444,
        "OrderDate": "/Date(867145390000)/",
        "RequiredDate": "/Date(176452694000)/",
        "ShippedDate": "/Date(138531717000)/",
        "ShipVia": 290137738,
        "Freight": 48007879336.3645,
        "ShipName": "ShipName13",
        "ShipAddress": "ShipAddress13",
        "ShipCity": "ShipCity13",
        "ShipRegion": "ShipRegion13",
        "ShipPostalCode": "ShipPost13",
        "ShipCountry": "ShipCountry13",
        "CompanyName": "zyRUNBGMaMKMNUYyWuUGcAAAsjvmpgXe",
        "Address": "Address13",
        "City": "City13",
        "Region": "Region13",
        "PostalCode": "PostalCo13",
        "Country": "Country13"
    },
    {
        "OrderID": 313589222,
        "CustomerID": "Cus14",
        "EmployeeID": 1093991933,
        "OrderDate": "/Date(1291076370000)/",
        "RequiredDate": "/Date(1265186167000)/",
        "ShippedDate": "/Date(674933642000)/",
        "ShipVia": 845773443,
        "Freight": 71416532224.9755,
        "ShipName": "ShipName14",
        "ShipAddress": "ShipAddress14",
        "ShipCity": "ShipCity14",
        "ShipRegion": "ShipRegion14",
        "ShipPostalCode": "ShipPost14",
        "ShipCountry": "ShipCountry14",
        "CompanyName": "ZWdvcEMBvymDMgJDpijmbZpBgCopyjnu",
        "Address": "Address14",
        "City": "City14",
        "Region": "Region14",
        "PostalCode": "PostalCo14",
        "Country": "Country14"
    },
    {
        "OrderID": 279520179,
        "CustomerID": "Cus15",
        "EmployeeID": 1891257499,
        "OrderDate": "/Date(697229340000)/",
        "RequiredDate": "/Date(378770758000)/",
        "ShippedDate": "/Date(18424434000)/",
        "ShipVia": 78608476,
        "Freight": 93375277868.472,
        "ShipName": "ShipName15",
        "ShipAddress": "ShipAddress15",
        "ShipCity": "ShipCity15",
        "ShipRegion": "ShipRegion15",
        "ShipPostalCode": "ShipPost15",
        "ShipCountry": "ShipCountry15",
        "CompanyName": "PlCQjzyYpKuTDgjGJiWePdsqgMinHjxd",
        "Address": "Address15",
        "City": "City15",
        "Region": "Region15",
        "PostalCode": "PostalCo15",
        "Country": "Country15"
    },
    {
        "OrderID": 410448943,
        "CustomerID": "Cus16",
        "EmployeeID": 1736621254,
        "OrderDate": "/Date(327036354000)/",
        "RequiredDate": "/Date(609514972000)/",
        "ShippedDate": "/Date(166316666000)/",
        "ShipVia": 403814854,
        "Freight": 59843887179.1586,
        "ShipName": "ShipName16",
        "ShipAddress": "ShipAddress16",
        "ShipCity": "ShipCity16",
        "ShipRegion": "ShipRegion16",
        "ShipPostalCode": "ShipPost16",
        "ShipCountry": "ShipCountry16",
        "CompanyName": "PBOZxcCaprRQKvOBRoWQuaicmSGYzDmn",
        "Address": "Address16",
        "City": "City16",
        "Region": "Region16",
        "PostalCode": "PostalCo16",
        "Country": "Country16"
    },
    {
        "OrderID": 2091737193,
        "CustomerID": "Cus17",
        "EmployeeID": 196820932,
        "OrderDate": "/Date(1136739902000)/",
        "RequiredDate": "/Date(1248561126000)/",
        "ShippedDate": "/Date(495129436000)/",
        "ShipVia": 1536452283,
        "Freight": 15971203963.2722,
        "ShipName": "ShipName17",
        "ShipAddress": "ShipAddress17",
        "ShipCity": "ShipCity17",
        "ShipRegion": "ShipRegion17",
        "ShipPostalCode": "ShipPost17",
        "ShipCountry": "ShipCountry17",
        "CompanyName": "uYLiltEFCnigDQkfpvUcPhuocyRQFMbJ",
        "Address": "Address17",
        "City": "City17",
        "Region": "Region17",
        "PostalCode": "PostalCo17",
        "Country": "Country17"
    },
    {
        "OrderID": 978486284,
        "CustomerID": "Cus18",
        "EmployeeID": 1511528917,
        "OrderDate": "/Date(207625369000)/",
        "RequiredDate": "/Date(1246548205000)/",
        "ShippedDate": "/Date(1219234893000)/",
        "ShipVia": 727923464,
        "Freight": 99225285882.1302,
        "ShipName": "ShipName18",
        "ShipAddress": "ShipAddress18",
        "ShipCity": "ShipCity18",
        "ShipRegion": "ShipRegion18",
        "ShipPostalCode": "ShipPost18",
        "ShipCountry": "ShipCountry18",
        "CompanyName": "SpsVhtQEkxKJLKuuMxmockpHtLiJwAOr",
        "Address": "Address18",
        "City": "City18",
        "Region": "Region18",
        "PostalCode": "PostalCo18",
        "Country": "Country18"
    },
    {
        "OrderID": 1369753402,
        "CustomerID": "Cus19",
        "EmployeeID": 2032009437,
        "OrderDate": "/Date(588234814000)/",
        "RequiredDate": "/Date(564414026000)/",
        "ShippedDate": "/Date(274190355000)/",
        "ShipVia": 1311155121,
        "Freight": 32863886305.131,
        "ShipName": "ShipName19",
        "ShipAddress": "ShipAddress19",
        "ShipCity": "ShipCity19",
        "ShipRegion": "ShipRegion19",
        "ShipPostalCode": "ShipPost19",
        "ShipCountry": "ShipCountry19",
        "CompanyName": "CrgUqMiucVfzrKospbXFNnklbasLWYbz",
        "Address": "Address19",
        "City": "City19",
        "Region": "Region19",
        "PostalCode": "PostalCo19",
        "Country": "Country19"
    },
    {
        "OrderID": 1394201127,
        "CustomerID": "Cus20",
        "EmployeeID": 30918703,
        "OrderDate": "/Date(787088274000)/",
        "RequiredDate": "/Date(699405353000)/",
        "ShippedDate": "/Date(839878040000)/",
        "ShipVia": 1207891317,
        "Freight": 45474777743.2203,
        "ShipName": "ShipName20",
        "ShipAddress": "ShipAddress20",
        "ShipCity": "ShipCity20",
        "ShipRegion": "ShipRegion20",
        "ShipPostalCode": "ShipPost20",
        "ShipCountry": "ShipCountry20",
        "CompanyName": "xATotUqDqHFYfjxpTBOPghJCHqgjaozf",
        "Address": "Address20",
        "City": "City20",
        "Region": "Region20",
        "PostalCode": "PostalCo20",
        "Country": "Country20"
    }
]