[
    {
        "CategoryName": "tTNaARbUfEVEvrX",
        "ProductName": "XSiGYdipgxOKZRspkDmUdkuAZtmDYRlE",
        "ProductSales": 29835657775.402
    },
    {
        "CategoryName": "PFXUcOkXKhQStrn",
        "ProductName": "zqfSEVTouHuEIRWSyLRVdoOfFeqewfHi",
        "ProductSales": 73519440181.5533
    },
    {
        "CategoryName": "ixUaPrYhJrUWJfh",
        "ProductName": "vXWOYSkjhsyJmLfZtjyugiUNQhGBOWHd",
        "ProductSales": 31082199024.9678
    },
    {
        "CategoryName": "DkkuHXPPFjSrapV",
        "ProductName": "LsvMQyahNEbBriEHdodLtKFrouJLowyM",
        "ProductSales": 81342726550.0649
    },
    {
        "CategoryName": "fyVDVWZzJFeSIVI",
        "ProductName": "VaSggXxaJiYDiaEouIeHrpthUlJDCswM",
        "ProductSales": 54124873969.7039
    },
    {
        "CategoryName": "sAvAObtBLhCosud",
        "ProductName": "VyCxSlJBUVomgbhuETMpVdGZZaYFthTV",
        "ProductSales": 35525510529.9875
    },
    {
        "CategoryName": "DBTHpSwPWCsypjt",
        "ProductName": "sAjvJtyjLsZNBKQJkJOIwNrtIIBIObAD",
        "ProductSales": 50681667053.1406
    },
    {
        "CategoryName": "ZGicKpXDGfvuVwN",
        "ProductName": "qhQkApAyGCOBKrYRKggdyTWsrBPPTzpf",
        "ProductSales": 1008859369.9038
    },
    {
        "CategoryName": "WzBgabarPWzwPcA",
        "ProductName": "FHMlskRGfUAiCDDHdpYrtctTKvmypDQo",
        "ProductSales": 81364925415.2551
    },
    {
        "CategoryName": "FkpckWoycVnsGsq",
        "ProductName": "OiKuyuPZsMlqJBJgtNqlERkymcJTCGEw",
        "ProductSales": 48020905745.2157
    },
    {
        "CategoryName": "VPmySpxYmbCuaLV",
        "ProductName": "PjWcSyWcIHxhqyPsVmyvWYlOFyYRMYoc",
        "ProductSales": 52601555921.1373
    },
    {
        "CategoryName": "BSioOMaUOfvkcvH",
        "ProductName": "MYZUHWeXFstsaYSsozVXBapufKxGiNIO",
        "ProductSales": 53759909188.3748
    },
    {
        "CategoryName": "auVwbyypIacjNMM",
        "ProductName": "XQjRCcAANNfAgMJaqKuWqNXAKOrfYwIM",
        "ProductSales": 86556216794.9974
    },
    {
        "CategoryName": "MgJnzWFzxsXPDTv",
        "ProductName": "DCGCrZDYtHJiCsuoceIFQOpDnBaHUIwK",
        "ProductSales": 1587131526.3211
    },
    {
        "CategoryName": "PLIgezyRoFUxiXN",
        "ProductName": "UFiUQSPUmmqjXVaWZxzUwDXeKrvbHsPm",
        "ProductSales": 41019209544.1743
    },
    {
        "CategoryName": "djmspRApwlpkzzY",
        "ProductName": "HJvgEiLPYqyukTCamrZSlSjXymJneStm",
        "ProductSales": 45217282162.0479
    },
    {
        "CategoryName": "cSPhZUfcoMElXcC",
        "ProductName": "hsnQJZuEFqPmLEFZWnNnJfaLmmEDrgEa",
        "ProductSales": 84225104795.7688
    },
    {
        "CategoryName": "UfcQnkVSBgIFGqx",
        "ProductName": "iOWlvGqhSocGjjspyRPjkZwKqpVfEVQi",
        "ProductSales": 17057966906.5773
    },
    {
        "CategoryName": "rWdfGUQNQXiiptn",
        "ProductName": "SCBcctpcIUNeoPywcIddrHncANINDOXL",
        "ProductSales": 92410628753.7142
    },
    {
        "CategoryName": "NKLVDQQEMgkJZdV",
        "ProductName": "GVibHjEghbaUmHeXVatzycWshibQAkSF",
        "ProductSales": 65130774327.5538
    }
]